slidegen/__init__.py
slidegen/cli/__init__.py
slidegen/cli/build.py
slidegen/cli/init.py
slidegen/cli/layouts.py
slidegen/cli/main.py
slidegen/cli/validate.py
slidegen/conversation/__init__.py
slidegen/conversation/handler.py
slidegen/core/__init__.py
slidegen/core/generator.py
slidegen/core/registry.py
slidegen/layouts/__init__.py
slidegen/layouts/base.py
slidegen/layouts/blank.py
slidegen/layouts/bullet_list.py
slidegen/layouts/chart.py
slidegen/layouts/comparison.py
slidegen/layouts/image.py
slidegen/layouts/quote.py
slidegen/layouts/section_header.py
slidegen/layouts/table.py
slidegen/layouts/title.py
slidegen/layouts/two_column.py
slidegen/llm/__init__.py
slidegen/llm/client.py
slidegen/llm/models.py
slidegen/llm/prompts/__init__.py
slidegen/llm/prompts/builder.py
slidegen/llm/prompts/examples.py
slidegen/llm/prompts/system.py
slidegen/theming/__init__.py
slidegen/theming/theme.py
slidegen/validator/__init__.py
slidegen/validator/core.py
slidegen/validator/messages.py
slidegen_pptx-0.1.0.dist-info/METADATA
slidegen_pptx-0.1.0.dist-info/WHEEL
slidegen_pptx-0.1.0.dist-info/entry_points.txt
slidegen_pptx-0.1.0.dist-info/top_level.txt
slidegen_pptx-0.1.0.dist-info/RECORD
